kalyanafamily/__init__.py
kalyanafamily-0.1.dist-info/LICENSE
kalyanafamily-0.1.dist-info/METADATA
kalyanafamily-0.1.dist-info/WHEEL
kalyanafamily-0.1.dist-info/top_level.txt
kalyanafamily-0.1.dist-info/RECORD
